google_spell_checker/__init__.py
google_spell_checker/google_spell_checker.py
google_spell_checker-0.2.1.dist-info/LICENSE
google_spell_checker-0.2.1.dist-info/METADATA
google_spell_checker-0.2.1.dist-info/WHEEL
google_spell_checker-0.2.1.dist-info/top_level.txt
google_spell_checker-0.2.1.dist-info/RECORD
