Metadata-Version: 2.1
Name: google-spell-checker
Version: 0.2.1
Summary: Google Spell Checker
Home-page: https://github.com/cahya-wirawan/google-spell-checker
Author: Cahya Wirawan
Author-email: cahya.wirawan@gmail.com
License: MIT
Platform: UNKNOWN
Classifier: License :: OSI Approved :: MIT License
Classifier: Operating System :: OS Independent
Classifier: Programming Language :: Python :: 3
Requires-Python: >=3.5
License-File: LICENSE
Requires-Dist: requests
